hardware_ml_benchmark/__init__.py
hardware_ml_benchmark/main.py
hardware_ml_benchmark/benchmark/__init__.py
hardware_ml_benchmark/benchmark/benchmarks.py
hardware_ml_benchmark/benchmark/monitoring.py
hardware_ml_benchmark/benchmark/rendering.py
hardware_ml_benchmark/core/__init__.py
hardware_ml_benchmark/core/cli.py
hardware_ml_benchmark/core/config.py
hardware_ml_benchmark/core/utils.py
hardware_ml_benchmark/data/__init__.py
hardware_ml_benchmark/data/datasets.py
hardware_ml_benchmark/models/__init__.py
hardware_ml_benchmark/models/models.py
hardware_ml_benchmark/output/__init__.py
hardware_ml_benchmark/output/output.py
hardware_ml_benchmark-0.2.1.dist-info/METADATA
hardware_ml_benchmark-0.2.1.dist-info/WHEEL
hardware_ml_benchmark-0.2.1.dist-info/entry_points.txt
hardware_ml_benchmark-0.2.1.dist-info/top_level.txt
hardware_ml_benchmark-0.2.1.dist-info/RECORD
