Metadata-Version: 2.4
Name: hardware-ml-benchmark
Version: 0.2.1
Summary: A hardware benchmarking tool for evaluating the inference performance of deep learning models. It supports pretrained tasks in image classification, object detection, and image segmentation, along with a variety of datasets.
Author-email: Wei Geng <wei.geng@tum.de>
Project-URL: Repository, https://github.com/ViGeng/hardware-bench-yolo.git
Project-URL: Homepage, https://github.com/ViGeng/hardware-bench-yolo
Keywords: deep learning,machine learning,hardware,benchmark,pytorch,performance,AI,inference,computer vision
Classifier: Development Status :: 4 - Beta
Classifier: Intended Audience :: Developers
Classifier: Intended Audience :: Science/Research
Classifier: Operating System :: OS Independent
Classifier: Programming Language :: Python :: 3
Classifier: Programming Language :: Python :: 3.8
Classifier: Programming Language :: Python :: 3.9
Classifier: Programming Language :: Python :: 3.10
Classifier: Programming Language :: Python :: 3.11
Classifier: Topic :: Scientific/Engineering :: Artificial Intelligence
Classifier: Topic :: Software Development :: Testing
Requires-Python: >=3.8
Requires-Dist: torch>=1.9.0
Requires-Dist: torchvision>=0.10.0
Requires-Dist: numpy>=1.19.0
Requires-Dist: psutil>=5.8.0
Requires-Dist: Pillow>=8.0.0
Requires-Dist: tqdm>=4.60.0
Requires-Dist: opencv-python
Requires-Dist: timm>=0.6.0
Provides-Extra: full
Requires-Dist: ultralytics>=8.0.0; extra == "full"
Requires-Dist: timm; extra == "full"
Requires-Dist: segmentation-models-pytorch>=0.3.0; extra == "full"
Requires-Dist: nvidia-ml-py3>=7.352.0; extra == "full"
Requires-Dist: matplotlib>=3.3.0; extra == "full"
Requires-Dist: seaborn>=0.11.0; extra == "full"
Provides-Extra: dev
Requires-Dist: pytest>=6.0; extra == "dev"
Requires-Dist: pytest-cov>=2.0; extra == "dev"
Requires-Dist: black>=21.0; extra == "dev"
Requires-Dist: flake8>=3.8; extra == "dev"
